luck_room_v1/LuckRoom.py
luck_room_v1/__init__.py
luck_room_v1-1.1.8.dist-info/licenses/LICENSE
luck_room_v1-1.1.8.dist-info/METADATA
luck_room_v1-1.1.8.dist-info/WHEEL
luck_room_v1-1.1.8.dist-info/entry_points.txt
luck_room_v1-1.1.8.dist-info/top_level.txt
luck_room_v1-1.1.8.dist-info/RECORD
