Metadata-Version: 2.4
Name: luck-room-v1
Version: 1.1.8
Summary: A simple luck based game.
Author-email: Braeden Sy Tan <braedenjairsytan@icloud.com>
License-Expression: GPL-3.0-only
Project-URL: Homepage, https://github.com/DuckyBoi-XD/Python-Learn-Gamble
Requires-Python: >=3.7
License-File: LICENSE
Dynamic: license-file
